xglider/__init__.py
xglider/cli.py
xglider/dev.py
xglider/netcdf.py
xglider/plot.py
xglider/xglider.py
xglider/netcdf_cfg/CORC.json
xglider/netcdf_cfg/CUGN.json
xglider/netcdf_cfg/GOM.json
xglider/netcdf_cfg/GulfStream.json
xglider/netcdf_cfg/Hawaii.json
xglider/netcdf_cfg/Solomon.json
xglider/netcdf_cfg/WHOI.json
xglider/netcdf_cfg/ngdac.json
xglider/netcdf_cfg/spray.json
xglider/netcdf_cfg/spray_ngdac.json
xglider/netcdf_cfg/trajectoryProfile_ragged2D.json
xglider/netcdf_cfg/xglider.json
xglider/netcdf_cfg/xglider_attrs_global.json
xglider/netcdf_cfg/xglider_globalattrs.json
xglider/netcdf_cfg/xglider_variables.json
xglider-0.0.2.dist-info/AUTHORS.rst
xglider-0.0.2.dist-info/LICENSE
xglider-0.0.2.dist-info/METADATA
xglider-0.0.2.dist-info/WHEEL
xglider-0.0.2.dist-info/entry_points.txt
xglider-0.0.2.dist-info/top_level.txt
xglider-0.0.2.dist-info/RECORD
